LICENSE.txt
MANIFEST.in
README.rst
dashconf.yml
dashgen.py
setup.py
examples/all_dash.yml
examples/all_graphs.yml
examples/cluster.yml
examples/pings.yml
python_graphite_dashgen.egg-info/PKG-INFO
python_graphite_dashgen.egg-info/SOURCES.txt
python_graphite_dashgen.egg-info/dependency_links.txt
python_graphite_dashgen.egg-info/requires.txt
python_graphite_dashgen.egg-info/top_level.txt