Metadata-Version: 1.1
Name: python-graphite-dashgen
Version: 0.1.3
Summary: Graphite-dashgen automates the creation of Graphite dashboards
Home-page: https://github.com/ClockworkNet/graphite-dashgen
Author: Timid Robot Zehta
Author-email: tim@clockwork.net
License: MIT License
Download-URL: https://github.com/ClockworkNet/graphite-dashgen/releases
Platform: UNKNOWN
Classifier: Environment :: Console
Classifier: Intended Audience :: System Administrators
Classifier: License :: OSI Approved :: MIT License
Classifier: Topic :: System :: Monitoring
Classifier: Topic :: Utilities
